LICENSE
MANIFEST.in
README.md
setup.py
vebench/__init__.py
vebench/evaluator.py
vebench/preprocess.py
vebench.egg-info/PKG-INFO
vebench.egg-info/SOURCES.txt
vebench.egg-info/dependency_links.txt
vebench.egg-info/requires.txt
vebench.egg-info/top_level.txt
vebench/blip_models/__init__.py
vebench/blip_models/blip.py
vebench/blip_models/blip_itm.py
vebench/blip_models/blip_nlvr.py
vebench/blip_models/blip_pretrain.py
vebench/blip_models/blip_retrieval.py
vebench/blip_models/blip_vqa.py
vebench/blip_models/med.py
vebench/blip_models/nlvr_encoder.py
vebench/blip_models/vit.py
vebench/configs/doublestream.yaml
vebench/configs/dover.yaml
vebench/configs/text.yaml
vebench/models/__init__.py
vebench/models/fidelity.py
vebench/models/head.py
vebench/models/network.py
vebench/models/text_alignment.py
vebench/models/tradition.py
vebench/models/backbone/__init__.py
vebench/models/backbone/blip.py
vebench/models/backbone/conv_backbone.py
vebench/models/backbone/swin_backbone.py
vebench/models/backbone/uniformer_backbone.py
vebench/models/backbone/BLIP_configs/bert_config.json
vebench/models/backbone/BLIP_configs/caption_coco.yaml
vebench/models/backbone/BLIP_configs/med_config.json
vebench/models/backbone/BLIP_configs/nlvr.yaml
vebench/models/backbone/BLIP_configs/nocaps.yaml
vebench/models/backbone/BLIP_configs/pretrain.yaml
vebench/models/backbone/BLIP_configs/retrieval_coco.yaml
vebench/models/backbone/BLIP_configs/retrieval_flickr.yaml
vebench/models/backbone/BLIP_configs/retrieval_msrvtt.yaml
vebench/models/backbone/BLIP_configs/vqa.yaml